plink_bed_reader/__init__.py
plink_bed_reader/plink_bed_reader.py
plink_bed_reader-1.0.2.dist-info/LICENSE
plink_bed_reader-1.0.2.dist-info/METADATA
plink_bed_reader-1.0.2.dist-info/WHEEL
plink_bed_reader-1.0.2.dist-info/top_level.txt
plink_bed_reader-1.0.2.dist-info/RECORD
