Metadata-Version: 2.1
Name: plink-bed-reader
Version: 1.0.2
Summary: Lightweight and memory efficient reader for PLINK BED files. It supports both SNP-major and individual-major formats. Written in pure Python.
Author-email: Rapsssito <contact@rodrigomartin.dev>
License: MIT
Project-URL: homepage, https://github.com/Computational-Genomics-BSC/plink-bed-reader
Project-URL: issues, https://github.com/Computational-Genomics-BSC/plink-bed-reader/issues
Project-URL: repository, https://github.com/Computational-Genomics-BSC/plink-bed-reader.git
Project-URL: documentation, https://computational-genomics-bsc.github.io/plink-bed-reader/
Keywords: bed,plink,genetics,bioinformatics,variant,indel,snv,genotype
Classifier: Programming Language :: Python :: 3 :: Only
Classifier: Development Status :: 5 - Production/Stable
Classifier: Operating System :: OS Independent
Requires-Python: >=3.6
License-File: LICENSE
Requires-Dist: numpy>=1.20.0
Provides-Extra: build
Requires-Dist: build~=1.2; extra == "build"
Provides-Extra: docs
Requires-Dist: sphinx; extra == "docs"
Requires-Dist: sphinx-rtd-theme; extra == "docs"
Requires-Dist: myst-parser; extra == "docs"
